CHANGELOG.txt
INSTALL.txt
LICENCE.txt
MANIFEST.in
README.txt
setup.cfg
setup.py
Starfive/__init__.py
Starfive.GPIO.egg-info/PKG-INFO
Starfive.GPIO.egg-info/SOURCES.txt
Starfive.GPIO.egg-info/dependency_links.txt
Starfive.GPIO.egg-info/top_level.txt
Starfive/GPIO/__init__.py
source/SHTC3_dev.c
source/SHTC3_dev.h
source/c_gpio.c
source/c_gpio.h
source/gpio-utils.c
source/gpio-utils.h
source/gpio.h
source/py_constants.c
source/py_constants.h
source/py_gpio.c
source/py_sense.c
source/py_sense.h
test/Sense_Hat.py